pymulty/__init__.py
pymulty-0.1.0.dist-info/licenses/LICENSE
pymulty-0.1.0.dist-info/METADATA
pymulty-0.1.0.dist-info/WHEEL
pymulty-0.1.0.dist-info/top_level.txt
pymulty-0.1.0.dist-info/RECORD
